[{"name":"AC","amount":22},{"name":"AL","amount":102},{"name":"AM","amount":62},{"name":"AP","amount":16},{"name":"BA","amount":417},{"name":"CE","amount":184},{"name":"DF","amount":1},{"name":"ES","amount":78},{"name":"GO","amount":246},{"name":"MA","amount":217},{"name":"MG","amount":853},{"name":"MS","amount":78},{"name":"MT","amount":140},{"name":"PA","amount":143},{"name":"PB","amount":223},{"name":"PE","amount":185},{"name":"PI","amount":223},{"name":"PR","amount":399},{"name":"RJ","amount":92},{"name":"RN","amount":167},{"name":"RO","amount":52},{"name":"RR","amount":15},{"name":"RS","amount":496},{"name":"SC","amount":293},{"name":"SE","amount":75},{"name":"SP","amount":645},{"name":"TO","amount":139}]